[
  {
    "id": "1",
    "name": "Nusr-Et Steakhouse",
    "neighborhood": "Etiler",
    "address": "Etiler, İstanbul",
    "phone": "+90 212 123 4567",
    "website": "https://www.nusr-et.com.tr",
    "cuisine": ["Steakhouse", "Et"],
    "price_level": 4,
    "rating": 4.8,
    "opening_hours": "10:00 - 23:00",
    "description": "Şık ambiyans, kaliteli etler ve fine dining deneyimi.",
    "tags": ["luks", "et", "fine dining"],
    "images": ["luxury1.jpg"],
    "coordinates": { "latitude": 41.066, "longitude": 29.022 },
    "sources": ["Nusr-Et Website", "Zomato"],
    "categories": ["Lüks Restoranlar"]
  },
  {
    "id": "2",
    "name": "Spago İstanbul",
    "neighborhood": "Nişantaşı",
    "address": "Nişantaşı, İstanbul",
    "phone": "+90 212 234 5678",
    "website": "https://www.spago.com.tr",
    "cuisine": ["International", "Fine Dining"],
    "price_level": 5,
    "rating": 4.7,
    "opening_hours": "12:00 - 23:00",
    "description": "Wolfgang Puck imzasıyla eşsiz manzaralı restoran.",
    "tags": ["luks", "fine dining"],
    "images": ["luxury2.jpg"],
    "coordinates": { "latitude": 41.067, "longitude": 29.019 },
    "sources": ["Spago Website", "Tripadvisor"],
    "categories": ["Lüks Restoranlar"]
  },
  {
    "id": "3",
    "name": "Mikla",
    "neighborhood": "Beyoğlu",
    "address": "Beyoğlu, İstanbul",
    "phone": "+90 212 345 6789",
    "website": "https://www.mikla.com.tr",
    "cuisine": ["Modern Turkish", "Fine Dining"],
    "price_level": 5,
    "rating": 4.9,
    "opening_hours": "17:00 - 23:00",
    "description": "Modern Türk mutfağı ve büyüleyici İstanbul manzarası.",
    "tags": ["luks", "fine dining", "manzara"],
    "images": ["luxury3.jpg"],
    "coordinates": { "latitude": 41.030, "longitude": 28.980 },
    "sources": ["Mikla Website", "Yelp"],
    "categories": ["Lüks Restoranlar"]
  },
  {
    "id": "4",
    "name": "Sunset Grill & Bar",
    "neighborhood": "Ulus",
    "address": "Ulus, İstanbul",
    "phone": "+90 212 456 7890",
    "website": "https://www.sunsetgrillbar.com",
    "cuisine": ["International", "Seafood"],
    "price_level": 5,
    "rating": 4.6,
    "opening_hours": "12:00 - 24:00",
    "description": "Boğaz manzarası ve dünya mutfağı seçenekleriyle özel günlerin adresi.",
    "tags": ["luks", "manzara", "deniz"],
    "images": ["luxury4.jpg"],
    "coordinates": { "latitude": 41.070, "longitude": 29.020 },
    "sources": ["Sunset Website", "Tripadvisor"],
    "categories": ["Lüks Restoranlar"]
  },
  {
    "id": "5",
    "name": "Ulus 29",
    "neighborhood": "Ulus",
    "address": "Ulus, İstanbul",
    "phone": "+90 212 567 8901",
    "website": "https://www.ulus29.com.tr",
    "cuisine": ["Turkish", "Fine Dining"],
    "price_level": 5,
    "rating": 4.7,
    "opening_hours": "11:00 - 23:00",
    "description": "Fine dining, lounge ve eşsiz manzara bir arada.",
    "tags": ["luks", "fine dining", "manzara"],
    "images": ["luxury5.jpg"],
    "coordinates": { "latitude": 41.071, "longitude": 29.021 },
    "sources": ["Ulus29 Website", "Yelp"],
    "categories": ["Lüks Restoranlar"]
  },
  {
    "id": "6",
    "name": "Develi Kebap",
    "neighborhood": "Samatya",
    "address": "Samatya, İstanbul",
    "phone": "+90 212 678 9012",
    "website": "https://www.develi.com.tr",
    "cuisine": ["Turkish", "Kebap"],
    "price_level": 3,
    "rating": 4.6,
    "opening_hours": "10:00 - 22:00",
    "description": "Geleneksel kebaplar ve meze çeşitleriyle meşhur mekan.",
    "tags": ["turk", "kebap"],
    "images": ["turkish1.jpg"],
    "coordinates": { "latitude": 41.025, "longitude": 28.960 },
    "sources": ["Develi Website", "Zomato"],
    "categories": ["Türk Mutfağı"]
  },
  {
    "id": "7",
    "name": "Köşebaşı",
    "neighborhood": "Levent",
    "address": "Levent, İstanbul",
    "phone": "+90 212 789 0123",
    "website": "https://www.kosebasi.com.tr",
    "cuisine": ["Turkish", "Kebap"],
    "price_level": 4,
    "rating": 4.5,
    "opening_hours": "11:00 - 23:00",
    "description": "Etin en lezzetli halini sunan geleneksel restoran.",
    "tags": ["turk", "et"],
    "images": ["turkish2.jpg"],
    "coordinates": { "latitude": 41.030, "longitude": 28.965 },
    "sources": ["Kosebasi Website", "Tripadvisor"],
    "categories": ["Türk Mutfağı"]
  },
  {
    "id": "8",
    "name": "Çiya Sofrası",
    "neighborhood": "Kadıköy",
    "address": "Kadıköy, İstanbul",
    "phone": "+90 216 890 1234",
    "website": "https://www.ciya.com.tr",
    "cuisine": ["Turkish", "Regional"],
    "price_level": 3,
    "rating": 4.8,
    "opening_hours": "09:00 - 22:00",
    "description": "Anadolu mutfağının en özel lezzetleriyle ünlü.",
    "tags": ["turk", "anadolu"],
    "images": ["turkish3.jpg"],
    "coordinates": { "latitude": 40.990, "longitude": 29.020 },
    "sources": ["Ciya Website", "Yelp"],
    "categories": ["Türk Mutfağı"]
  },
  {
    "id": "9",
    "name": "Günaydın Et Lokantası",
    "neighborhood": "Ataşehir",
    "address": "Ataşehir, İstanbul",
    "phone": "+90 216 901 2345",
    "website": "https://www.gunaydin.com.tr",
    "cuisine": ["Turkish", "Steakhouse"],
    "price_level": 4,
    "rating": 4.6,
    "opening_hours": "10:00 - 23:00",
    "description": "Et ustalığı ve kebap çeşitleriyle bilinen popüler mekan.",
    "tags": ["turk", "et"],
    "images": ["turkish4.jpg"],
    "coordinates": { "latitude": 41.015, "longitude": 29.080 },
    "sources": ["Gunaydin Website", "Zomato"],
    "categories": ["Türk Mutfağı"]
  },
  {
    "id": "10",
    "name": "Şazeli",
    "neighborhood": "Tarabya",
    "address": "Tarabya, İstanbul",
    "phone": "+90 212 345 6780",
    "website": "https://www.shazeli.com.tr",
    "cuisine": ["Turkish", "Seafood"],
    "price_level": 4,
    "rating": 4.7,
    "opening_hours": "11:00 - 22:00",
    "description": "Manzaralı, geleneksel Türk mutfağı restoranı.",
    "tags": ["turk", "deniz", "manzara"],
    "images": ["turkish5.jpg"],
    "coordinates": { "latitude": 41.090, "longitude": 29.020 },
    "sources": ["Shazeli Website", "Tripadvisor"],
    "categories": ["Türk Mutfağı"]
  }
]
